nonebot_plugin_netrunner/__init__.py
nonebot_plugin_netrunner-0.1.3.dist-info/LICENSE
nonebot_plugin_netrunner-0.1.3.dist-info/METADATA
nonebot_plugin_netrunner-0.1.3.dist-info/WHEEL
nonebot_plugin_netrunner-0.1.3.dist-info/RECORD
