Metadata-Version: 2.1
Name: nonebot-plugin-netrunner
Version: 0.1.3
Summary: a NoneBot plugin for Netrunner.
Home-page: https://github.com/eric03742/nonebot-plugin-netrunner
License: MIT
Author: Eric Li
Author-email: eric03742@foxmail.com
Requires-Python: >=3.9.0,<4.0.0
Classifier: License :: OSI Approved :: MIT License
Classifier: Programming Language :: Python :: 3
Classifier: Programming Language :: Python :: 3.9
Classifier: Programming Language :: Python :: 3.10
Classifier: Programming Language :: Python :: 3.11
Classifier: Programming Language :: Python :: 3.12
Classifier: Programming Language :: Python :: 3.13
Requires-Dist: httpx (>=0.27.2,<0.28.0)
Requires-Dist: nonebot-adapter-onebot (>=2.4.5,<3.0.0)
Requires-Dist: nonebot2 (>=2.3.3,<3.0.0)
Project-URL: Repository, https://github.com/eric03742/nonebot-plugin-netrunner
